{"nodes": [{"id": "users_praveenkumar_documents_project_freelance_ims_v2_docs_architecture_brd_brd_md", "label": "BRD.md", "file_type": "document", "source_file": "docs/architecture/brd/BRD.md", "source_location": "L1"}, {"id": "brd_brd_business_requirements_document_brd", "label": "Business Requirements Document (BRD)", "file_type": "document", "source_file": "docs/architecture/brd/BRD.md", "source_location": "L5"}, {"id": "brd_brd_institute_management_system_ims", "label": "Institute Management System (IMS)", "file_type": "document", "source_file": "docs/architecture/brd/BRD.md", "source_location": "L7"}, {"id": "brd_brd_version_1_0", "label": "Version 1.0", "file_type": "document", "source_file": "docs/architecture/brd/BRD.md", "source_location": "L9"}, {"id": "brd_brd_status_draft", "label": "Status: Draft", "file_type": "document", "source_file": "docs/architecture/brd/BRD.md", "source_location": "L11"}, {"id": "brd_brd_client_al_saud_international_initial_implementation", "label": "Client: Al Saud International (Initial Implementation)", "file_type": "document", "source_file": "docs/architecture/brd/BRD.md", "source_location": "L13"}, {"id": "brd_brd_prepared_by_product_discovery_phase", "label": "Prepared By: Product Discovery Phase", "file_type": "document", "source_file": "docs/architecture/brd/BRD.md", "source_location": "L15"}, {"id": "brd_brd_target_market_oman_training_coaching_institutes", "label": "Target Market: Oman Training & Coaching Institutes", "file_type": "document", "source_file": "docs/architecture/brd/BRD.md", "source_location": "L17"}, {"id": "brd_brd_1_document_purpose", "label": "1. Document Purpose", "file_type": "document", "source_file": "docs/architecture/brd/BRD.md", "source_location": "L21"}, {"id": "brd_brd_2_business_problem_statement", "label": "2. Business Problem Statement", "file_type": "document", "source_file": "docs/architecture/brd/BRD.md", "source_location": "L41"}, {"id": "brd_brd_operational_issues", "label": "Operational Issues", "file_type": "document", "source_file": "docs/architecture/brd/BRD.md", "source_location": "L54"}, {"id": "brd_brd_management_issues", "label": "Management Issues", "file_type": "document", "source_file": "docs/architecture/brd/BRD.md", "source_location": "L64"}, {"id": "brd_brd_3_business_objectives", "label": "3. Business Objectives", "file_type": "document", "source_file": "docs/architecture/brd/BRD.md", "source_location": "L74"}, {"id": "brd_brd_bo_001", "label": "BO-001", "file_type": "document", "source_file": "docs/architecture/brd/BRD.md", "source_location": "L78"}, {"id": "brd_brd_bo_002", "label": "BO-002", "file_type": "document", "source_file": "docs/architecture/brd/BRD.md", "source_location": "L82"}, {"id": "brd_brd_bo_003", "label": "BO-003", "file_type": "document", "source_file": "docs/architecture/brd/BRD.md", "source_location": "L86"}, {"id": "brd_brd_bo_004", "label": "BO-004", "file_type": "document", "source_file": "docs/architecture/brd/BRD.md", "source_location": "L90"}, {"id": "brd_brd_bo_005", "label": "BO-005", "file_type": "document", "source_file": "docs/architecture/brd/BRD.md", "source_location": "L94"}, {"id": "brd_brd_bo_006", "label": "BO-006", "file_type": "document", "source_file": "docs/architecture/brd/BRD.md", "source_location": "L98"}, {"id": "brd_brd_bo_007", "label": "BO-007", "file_type": "document", "source_file": "docs/architecture/brd/BRD.md", "source_location": "L102"}, {"id": "brd_brd_4_project_scope", "label": "4. Project Scope", "file_type": "document", "source_file": "docs/architecture/brd/BRD.md", "source_location": "L108"}, {"id": "brd_brd_in_scope", "label": "In Scope", "file_type": "document", "source_file": "docs/architecture/brd/BRD.md", "source_location": "L110"}, {"id": "brd_brd_administration", "label": "Administration", "file_type": "document", "source_file": "docs/architecture/brd/BRD.md", "source_location": "L112"}, {"id": "brd_brd_organization", "label": "Organization", "file_type": "document", "source_file": "docs/architecture/brd/BRD.md", "source_location": "L118"}, {"id": "brd_brd_crm", "label": "CRM", "file_type": "document", "source_file": "docs/architecture/brd/BRD.md", "source_location": "L123"}, {"id": "brd_brd_students", "label": "Students", "file_type": "document", "source_file": "docs/architecture/brd/BRD.md", "source_location": "L129"}, {"id": "brd_brd_corporate", "label": "Corporate", "file_type": "document", "source_file": "docs/architecture/brd/BRD.md", "source_location": "L135"}, {"id": "brd_brd_academics", "label": "Academics", "file_type": "document", "source_file": "docs/architecture/brd/BRD.md", "source_location": "L141"}, {"id": "brd_brd_finance", "label": "Finance", "file_type": "document", "source_file": "docs/architecture/brd/BRD.md", "source_location": "L148"}, {"id": "brd_brd_communication", "label": "Communication", "file_type": "document", "source_file": "docs/architecture/brd/BRD.md", "source_location": "L156"}, {"id": "brd_brd_certificates", "label": "Certificates", "file_type": "document", "source_file": "docs/architecture/brd/BRD.md", "source_location": "L162"}, {"id": "brd_brd_reporting", "label": "Reporting", "file_type": "document", "source_file": "docs/architecture/brd/BRD.md", "source_location": "L167"}, {"id": "brd_brd_out_of_scope_current_release", "label": "Out of Scope (Current Release)", "file_type": "document", "source_file": "docs/architecture/brd/BRD.md", "source_location": "L174"}, {"id": "brd_brd_saas_features", "label": "SaaS Features", "file_type": "document", "source_file": "docs/architecture/brd/BRD.md", "source_location": "L176"}, {"id": "brd_brd_cms_features", "label": "CMS Features", "file_type": "document", "source_file": "docs/architecture/brd/BRD.md", "source_location": "L182"}, {"id": "brd_brd_future_features", "label": "Future Features", "file_type": "document", "source_file": "docs/architecture/brd/BRD.md", "source_location": "L188"}, {"id": "brd_brd_in_scope_for_architecture_phased_for_delivery", "label": "In Scope for Architecture, Phased for Delivery", "file_type": "document", "source_file": "docs/architecture/brd/BRD.md", "source_location": "L194"}, {"id": "brd_brd_5_stakeholders", "label": "5. Stakeholders", "file_type": "document", "source_file": "docs/architecture/brd/BRD.md", "source_location": "L201"}, {"id": "brd_brd_6_user_roles", "label": "6. User Roles", "file_type": "document", "source_file": "docs/architecture/brd/BRD.md", "source_location": "L216"}, {"id": "brd_brd_owner", "label": "Owner", "file_type": "document", "source_file": "docs/architecture/brd/BRD.md", "source_location": "L218"}, {"id": "brd_brd_branch_manager", "label": "Branch Manager", "file_type": "document", "source_file": "docs/architecture/brd/BRD.md", "source_location": "L228"}, {"id": "brd_brd_counselor", "label": "Counselor", "file_type": "document", "source_file": "docs/architecture/brd/BRD.md", "source_location": "L239"}, {"id": "brd_brd_faculty", "label": "Faculty", "file_type": "document", "source_file": "docs/architecture/brd/BRD.md", "source_location": "L249"}, {"id": "brd_brd_accountant", "label": "Accountant", "file_type": "document", "source_file": "docs/architecture/brd/BRD.md", "source_location": "L259"}, {"id": "brd_brd_student", "label": "Student", "file_type": "document", "source_file": "docs/architecture/brd/BRD.md", "source_location": "L270"}, {"id": "brd_brd_7_functional_requirements", "label": "7. Functional Requirements", "file_type": "document", "source_file": "docs/architecture/brd/BRD.md", "source_location": "L282"}, {"id": "brd_brd_fr_01_user_management", "label": "FR-01 User Management", "file_type": "document", "source_file": "docs/architecture/brd/BRD.md", "source_location": "L286"}, {"id": "brd_brd_fr_02_dynamic_role_management", "label": "FR-02 Dynamic Role Management", "file_type": "document", "source_file": "docs/architecture/brd/BRD.md", "source_location": "L297"}, {"id": "brd_brd_fr_03_branch_management", "label": "FR-03 Branch Management", "file_type": "document", "source_file": "docs/architecture/brd/BRD.md", "source_location": "L310"}, {"id": "brd_brd_fr_04_department_management", "label": "FR-04 Department Management", "file_type": "document", "source_file": "docs/architecture/brd/BRD.md", "source_location": "L320"}, {"id": "brd_brd_fr_05_lead_management", "label": "FR-05 Lead Management", "file_type": "document", "source_file": "docs/architecture/brd/BRD.md", "source_location": "L333"}, {"id": "brd_brd_lead_sources", "label": "Lead Sources", "file_type": "document", "source_file": "docs/architecture/brd/BRD.md", "source_location": "L337"}, {"id": "brd_brd_lead_stages", "label": "Lead Stages", "file_type": "document", "source_file": "docs/architecture/brd/BRD.md", "source_location": "L346"}, {"id": "brd_brd_follow_up_management", "label": "Follow-up Management", "file_type": "document", "source_file": "docs/architecture/brd/BRD.md", "source_location": "L359"}, {"id": "brd_brd_fr_06_admission_management", "label": "FR-06 Admission Management", "file_type": "document", "source_file": "docs/architecture/brd/BRD.md", "source_location": "L367"}, {"id": "brd_brd_fr_07_student_management", "label": "FR-07 Student Management", "file_type": "document", "source_file": "docs/architecture/brd/BRD.md", "source_location": "L378"}, {"id": "brd_brd_student_profile", "label": "Student Profile", "file_type": "document", "source_file": "docs/architecture/brd/BRD.md", "source_location": "L382"}, {"id": "brd_brd_student_status", "label": "Student Status", "file_type": "document", "source_file": "docs/architecture/brd/BRD.md", "source_location": "L388"}, {"id": "brd_brd_fr_08_corporate_customer_management", "label": "FR-08 Corporate Customer Management", "file_type": "document", "source_file": "docs/architecture/brd/BRD.md", "source_location": "L404"}, {"id": "brd_brd_corporate_profiles", "label": "Corporate Profiles", "file_type": "document", "source_file": "docs/architecture/brd/BRD.md", "source_location": "L408"}, {"id": "brd_brd_corporate_contracts", "label": "Corporate Contracts", "file_type": "document", "source_file": "docs/architecture/brd/BRD.md", "source_location": "L413"}, {"id": "brd_brd_corporate_employees", "label": "Corporate Employees", "file_type": "document", "source_file": "docs/architecture/brd/BRD.md", "source_location": "L420"}, {"id": "brd_brd_fr_09_course_management", "label": "FR-09 Course Management", "file_type": "document", "source_file": "docs/architecture/brd/BRD.md", "source_location": "L427"}, {"id": "brd_brd_course_types", "label": "Course Types", "file_type": "document", "source_file": "docs/architecture/brd/BRD.md", "source_location": "L431"}, {"id": "brd_brd_duration_types", "label": "Duration Types", "file_type": "document", "source_file": "docs/architecture/brd/BRD.md", "source_location": "L439"}, {"id": "brd_brd_fr_10_batch_management", "label": "FR-10 Batch Management", "file_type": "document", "source_file": "docs/architecture/brd/BRD.md", "source_location": "L447"}, {"id": "brd_brd_batch_features", "label": "Batch Features", "file_type": "document", "source_file": "docs/architecture/brd/BRD.md", "source_location": "L451"}, {"id": "brd_brd_fr_11_timetable_management", "label": "FR-11 Timetable Management", "file_type": "document", "source_file": "docs/architecture/brd/BRD.md", "source_location": "L459"}, {"id": "brd_brd_conflict_detection", "label": "Conflict Detection", "file_type": "document", "source_file": "docs/architecture/brd/BRD.md", "source_location": "L467"}, {"id": "brd_brd_fr_12_attendance_management", "label": "FR-12 Attendance Management", "file_type": "document", "source_file": "docs/architecture/brd/BRD.md", "source_location": "L477"}, {"id": "brd_brd_fr_13_fee_management", "label": "FR-13 Fee Management", "file_type": "document", "source_file": "docs/architecture/brd/BRD.md", "source_location": "L488"}, {"id": "brd_brd_fee_models", "label": "Fee Models", "file_type": "document", "source_file": "docs/architecture/brd/BRD.md", "source_location": "L492"}, {"id": "brd_brd_discounts", "label": "Discounts", "file_type": "document", "source_file": "docs/architecture/brd/BRD.md", "source_location": "L497"}, {"id": "brd_brd_refunds", "label": "Refunds", "file_type": "document", "source_file": "docs/architecture/brd/BRD.md", "source_location": "L506"}, {"id": "brd_brd_fr_14_communication_module", "label": "FR-14 Communication Module", "file_type": "document", "source_file": "docs/architecture/brd/BRD.md", "source_location": "L513"}, {"id": "brd_brd_channels", "label": "Channels", "file_type": "document", "source_file": "docs/architecture/brd/BRD.md", "source_location": "L517"}, {"id": "brd_brd_features", "label": "Features", "file_type": "document", "source_file": "docs/architecture/brd/BRD.md", "source_location": "L523"}, {"id": "brd_brd_fr_15_certificate_management", "label": "FR-15 Certificate Management", "file_type": "document", "source_file": "docs/architecture/brd/BRD.md", "source_location": "L532"}, {"id": "brd_brd_auto_certificate_generation", "label": "Auto Certificate Generation", "file_type": "document", "source_file": "docs/architecture/brd/BRD.md", "source_location": "L536"}, {"id": "brd_brd_eligibility_rules", "label": "Eligibility Rules", "file_type": "document", "source_file": "docs/architecture/brd/BRD.md", "source_location": "L540"}, {"id": "brd_brd_verification", "label": "Verification", "file_type": "document", "source_file": "docs/architecture/brd/BRD.md", "source_location": "L547"}, {"id": "brd_brd_fr_16_document_management", "label": "FR-16 Document Management", "file_type": "document", "source_file": "docs/architecture/brd/BRD.md", "source_location": "L554"}, {"id": "brd_brd_student_documents", "label": "Student Documents", "file_type": "document", "source_file": "docs/architecture/brd/BRD.md", "source_location": "L558"}, {"id": "brd_brd_approval_workflow", "label": "Approval Workflow", "file_type": "document", "source_file": "docs/architecture/brd/BRD.md", "source_location": "L562"}, {"id": "brd_brd_fr_17_reporting_dashboard", "label": "FR-17 Reporting & Dashboard", "file_type": "document", "source_file": "docs/architecture/brd/BRD.md", "source_location": "L573"}, {"id": "brd_brd_operational_reports", "label": "Operational Reports", "file_type": "document", "source_file": "docs/architecture/brd/BRD.md", "source_location": "L577"}, {"id": "brd_brd_business_reports", "label": "Business Reports", "file_type": "document", "source_file": "docs/architecture/brd/BRD.md", "source_location": "L584"}, {"id": "brd_brd_8_non_functional_requirements", "label": "8. Non-Functional Requirements", "file_type": "document", "source_file": "docs/architecture/brd/BRD.md", "source_location": "L594"}, {"id": "brd_brd_performance", "label": "Performance", "file_type": "document", "source_file": "docs/architecture/brd/BRD.md", "source_location": "L596"}, {"id": "brd_brd_security", "label": "Security", "file_type": "document", "source_file": "docs/architecture/brd/BRD.md", "source_location": "L606"}, {"id": "brd_brd_auditability", "label": "Auditability", "file_type": "document", "source_file": "docs/architecture/brd/BRD.md", "source_location": "L616"}, {"id": "brd_brd_localization", "label": "Localization", "file_type": "document", "source_file": "docs/architecture/brd/BRD.md", "source_location": "L627"}, {"id": "brd_brd_availability", "label": "Availability", "file_type": "document", "source_file": "docs/architecture/brd/BRD.md", "source_location": "L637"}, {"id": "brd_brd_9_success_metrics", "label": "9. Success Metrics", "file_type": "document", "source_file": "docs/architecture/brd/BRD.md", "source_location": "L647"}, {"id": "brd_brd_lead_management", "label": "Lead Management", "file_type": "document", "source_file": "docs/architecture/brd/BRD.md", "source_location": "L651"}, {"id": "brd_brd_admissions", "label": "Admissions", "file_type": "document", "source_file": "docs/architecture/brd/BRD.md", "source_location": "L655"}, {"id": "brd_brd_attendance", "label": "Attendance", "file_type": "document", "source_file": "docs/architecture/brd/BRD.md", "source_location": "L659"}, {"id": "brd_brd_finance_663", "label": "Finance", "file_type": "document", "source_file": "docs/architecture/brd/BRD.md", "source_location": "L663"}, {"id": "brd_brd_reporting_667", "label": "Reporting", "file_type": "document", "source_file": "docs/architecture/brd/BRD.md", "source_location": "L667"}, {"id": "brd_brd_10_future_roadmap", "label": "10. Future Roadmap", "file_type": "document", "source_file": "docs/architecture/brd/BRD.md", "source_location": "L673"}, {"id": "brd_brd_phase_2", "label": "Phase 2", "file_type": "document", "source_file": "docs/architecture/brd/BRD.md", "source_location": "L675"}, {"id": "brd_brd_phase_3", "label": "Phase 3", "file_type": "document", "source_file": "docs/architecture/brd/BRD.md", "source_location": "L682"}, {"id": "brd_brd_phase_4", "label": "Phase 4", "file_type": "document", "source_file": "docs/architecture/brd/BRD.md", "source_location": "L690"}, {"id": "brd_brd_11_review_alignment_addendum", "label": "11. Review Alignment Addendum", "file_type": "document", "source_file": "docs/architecture/brd/BRD.md", "source_location": "L699"}, {"id": "brd_brd_b2b_corporate_training_requirements", "label": "B2B Corporate Training Requirements", "file_type": "document", "source_file": "docs/architecture/brd/BRD.md", "source_location": "L703"}, {"id": "brd_brd_compliance_and_document_expiry_requirements", "label": "Compliance and Document Expiry Requirements", "file_type": "document", "source_file": "docs/architecture/brd/BRD.md", "source_location": "L716"}, {"id": "brd_brd_bilingual_data_requirements", "label": "Bilingual Data Requirements", "file_type": "document", "source_file": "docs/architecture/brd/BRD.md", "source_location": "L722"}, {"id": "brd_brd_offline_attendance_and_tally_reliability", "label": "Offline Attendance and Tally Reliability", "file_type": "document", "source_file": "docs/architecture/brd/BRD.md", "source_location": "L726"}], "edges": [{"source": "users_praveenkumar_documents_project_freelance_ims_v2_docs_architecture_brd_brd_md", "target": "brd_brd_business_requirements_document_brd", "relation": "contains", "confidence": "EXTRACTED", "source_file": "docs/architecture/brd/BRD.md", "source_location": "L5", "weight": 1.0}, {"source": "brd_brd_business_requirements_document_brd", "target": "brd_brd_institute_management_system_ims", "relation": "contains", "confidence": "EXTRACTED", "source_file": "docs/architecture/brd/BRD.md", "source_location": "L7", "weight": 1.0}, {"source": "brd_brd_institute_management_system_ims", "target": "brd_brd_version_1_0", "relation": "contains", "confidence": "EXTRACTED", "source_file": "docs/architecture/brd/BRD.md", "source_location": "L9", "weight": 1.0}, {"source": "brd_brd_institute_management_system_ims", "target": "brd_brd_status_draft", "relation": "contains", "confidence": "EXTRACTED", "source_file": "docs/architecture/brd/BRD.md", "source_location": "L11", "weight": 1.0}, {"source": "brd_brd_institute_management_system_ims", "target": "brd_brd_client_al_saud_international_initial_implementation", "relation": "contains", "confidence": "EXTRACTED", "source_file": "docs/architecture/brd/BRD.md", "source_location": "L13", "weight": 1.0}, {"source": "brd_brd_institute_management_system_ims", "target": "brd_brd_prepared_by_product_discovery_phase", "relation": "contains", "confidence": "EXTRACTED", "source_file": "docs/architecture/brd/BRD.md", "source_location": "L15", "weight": 1.0}, {"source": "brd_brd_institute_management_system_ims", "target": "brd_brd_target_market_oman_training_coaching_institutes", "relation": "contains", "confidence": "EXTRACTED", "source_file": "docs/architecture/brd/BRD.md", "source_location": "L17", "weight": 1.0}, {"source": "users_praveenkumar_documents_project_freelance_ims_v2_docs_architecture_brd_brd_md", "target": "brd_brd_1_document_purpose", "relation": "contains", "confidence": "EXTRACTED", "source_file": "docs/architecture/brd/BRD.md", "source_location": "L21", "weight": 1.0}, {"source": "users_praveenkumar_documents_project_freelance_ims_v2_docs_architecture_brd_brd_md", "target": "brd_brd_2_business_problem_statement", "relation": "contains", "confidence": "EXTRACTED", "source_file": "docs/architecture/brd/BRD.md", "source_location": "L41", "weight": 1.0}, {"source": "brd_brd_2_business_problem_statement", "target": "brd_brd_operational_issues", "relation": "contains", "confidence": "EXTRACTED", "source_file": "docs/architecture/brd/BRD.md", "source_location": "L54", "weight": 1.0}, {"source": "brd_brd_2_business_problem_statement", "target": "brd_brd_management_issues", "relation": "contains", "confidence": "EXTRACTED", "source_file": "docs/architecture/brd/BRD.md", "source_location": "L64", "weight": 1.0}, {"source": "users_praveenkumar_documents_project_freelance_ims_v2_docs_architecture_brd_brd_md", "target": "brd_brd_3_business_objectives", "relation": "contains", "confidence": "EXTRACTED", "source_file": "docs/architecture/brd/BRD.md", "source_location": "L74", "weight": 1.0}, {"source": "brd_brd_3_business_objectives", "target": "brd_brd_bo_001", "relation": "contains", "confidence": "EXTRACTED", "source_file": "docs/architecture/brd/BRD.md", "source_location": "L78", "weight": 1.0}, {"source": "brd_brd_3_business_objectives", "target": "brd_brd_bo_002", "relation": "contains", "confidence": "EXTRACTED", "source_file": "docs/architecture/brd/BRD.md", "source_location": "L82", "weight": 1.0}, {"source": "brd_brd_3_business_objectives", "target": "brd_brd_bo_003", "relation": "contains", "confidence": "EXTRACTED", "source_file": "docs/architecture/brd/BRD.md", "source_location": "L86", "weight": 1.0}, {"source": "brd_brd_3_business_objectives", "target": "brd_brd_bo_004", "relation": "contains", "confidence": "EXTRACTED", "source_file": "docs/architecture/brd/BRD.md", "source_location": "L90", "weight": 1.0}, {"source": "brd_brd_3_business_objectives", "target": "brd_brd_bo_005", "relation": "contains", "confidence": "EXTRACTED", "source_file": "docs/architecture/brd/BRD.md", "source_location": "L94", "weight": 1.0}, {"source": "brd_brd_3_business_objectives", "target": "brd_brd_bo_006", "relation": "contains", "confidence": "EXTRACTED", "source_file": "docs/architecture/brd/BRD.md", "source_location": "L98", "weight": 1.0}, {"source": "brd_brd_3_business_objectives", "target": "brd_brd_bo_007", "relation": "contains", "confidence": "EXTRACTED", "source_file": "docs/architecture/brd/BRD.md", "source_location": "L102", "weight": 1.0}, {"source": "users_praveenkumar_documents_project_freelance_ims_v2_docs_architecture_brd_brd_md", "target": "brd_brd_4_project_scope", "relation": "contains", "confidence": "EXTRACTED", "source_file": "docs/architecture/brd/BRD.md", "source_location": "L108", "weight": 1.0}, {"source": "brd_brd_4_project_scope", "target": "brd_brd_in_scope", "relation": "contains", "confidence": "EXTRACTED", "source_file": "docs/architecture/brd/BRD.md", "source_location": "L110", "weight": 1.0}, {"source": "brd_brd_in_scope", "target": "brd_brd_administration", "relation": "contains", "confidence": "EXTRACTED", "source_file": "docs/architecture/brd/BRD.md", "source_location": "L112", "weight": 1.0}, {"source": "brd_brd_in_scope", "target": "brd_brd_organization", "relation": "contains", "confidence": "EXTRACTED", "source_file": "docs/architecture/brd/BRD.md", "source_location": "L118", "weight": 1.0}, {"source": "brd_brd_in_scope", "target": "brd_brd_crm", "relation": "contains", "confidence": "EXTRACTED", "source_file": "docs/architecture/brd/BRD.md", "source_location": "L123", "weight": 1.0}, {"source": "brd_brd_in_scope", "target": "brd_brd_students", "relation": "contains", "confidence": "EXTRACTED", "source_file": "docs/architecture/brd/BRD.md", "source_location": "L129", "weight": 1.0}, {"source": "brd_brd_in_scope", "target": "brd_brd_corporate", "relation": "contains", "confidence": "EXTRACTED", "source_file": "docs/architecture/brd/BRD.md", "source_location": "L135", "weight": 1.0}, {"source": "brd_brd_in_scope", "target": "brd_brd_academics", "relation": "contains", "confidence": "EXTRACTED", "source_file": "docs/architecture/brd/BRD.md", "source_location": "L141", "weight": 1.0}, {"source": "brd_brd_in_scope", "target": "brd_brd_finance", "relation": "contains", "confidence": "EXTRACTED", "source_file": "docs/architecture/brd/BRD.md", "source_location": "L148", "weight": 1.0}, {"source": "brd_brd_in_scope", "target": "brd_brd_communication", "relation": "contains", "confidence": "EXTRACTED", "source_file": "docs/architecture/brd/BRD.md", "source_location": "L156", "weight": 1.0}, {"source": "brd_brd_in_scope", "target": "brd_brd_certificates", "relation": "contains", "confidence": "EXTRACTED", "source_file": "docs/architecture/brd/BRD.md", "source_location": "L162", "weight": 1.0}, {"source": "brd_brd_in_scope", "target": "brd_brd_reporting", "relation": "contains", "confidence": "EXTRACTED", "source_file": "docs/architecture/brd/BRD.md", "source_location": "L167", "weight": 1.0}, {"source": "brd_brd_4_project_scope", "target": "brd_brd_out_of_scope_current_release", "relation": "contains", "confidence": "EXTRACTED", "source_file": "docs/architecture/brd/BRD.md", "source_location": "L174", "weight": 1.0}, {"source": "brd_brd_out_of_scope_current_release", "target": "brd_brd_saas_features", "relation": "contains", "confidence": "EXTRACTED", "source_file": "docs/architecture/brd/BRD.md", "source_location": "L176", "weight": 1.0}, {"source": "brd_brd_out_of_scope_current_release", "target": "brd_brd_cms_features", "relation": "contains", "confidence": "EXTRACTED", "source_file": "docs/architecture/brd/BRD.md", "source_location": "L182", "weight": 1.0}, {"source": "brd_brd_out_of_scope_current_release", "target": "brd_brd_future_features", "relation": "contains", "confidence": "EXTRACTED", "source_file": "docs/architecture/brd/BRD.md", "source_location": "L188", "weight": 1.0}, {"source": "brd_brd_out_of_scope_current_release", "target": "brd_brd_in_scope_for_architecture_phased_for_delivery", "relation": "contains", "confidence": "EXTRACTED", "source_file": "docs/architecture/brd/BRD.md", "source_location": "L194", "weight": 1.0}, {"source": "users_praveenkumar_documents_project_freelance_ims_v2_docs_architecture_brd_brd_md", "target": "brd_brd_5_stakeholders", "relation": "contains", "confidence": "EXTRACTED", "source_file": "docs/architecture/brd/BRD.md", "source_location": "L201", "weight": 1.0}, {"source": "users_praveenkumar_documents_project_freelance_ims_v2_docs_architecture_brd_brd_md", "target": "brd_brd_6_user_roles", "relation": "contains", "confidence": "EXTRACTED", "source_file": "docs/architecture/brd/BRD.md", "source_location": "L216", "weight": 1.0}, {"source": "brd_brd_6_user_roles", "target": "brd_brd_owner", "relation": "contains", "confidence": "EXTRACTED", "source_file": "docs/architecture/brd/BRD.md", "source_location": "L218", "weight": 1.0}, {"source": "brd_brd_6_user_roles", "target": "brd_brd_branch_manager", "relation": "contains", "confidence": "EXTRACTED", "source_file": "docs/architecture/brd/BRD.md", "source_location": "L228", "weight": 1.0}, {"source": "brd_brd_6_user_roles", "target": "brd_brd_counselor", "relation": "contains", "confidence": "EXTRACTED", "source_file": "docs/architecture/brd/BRD.md", "source_location": "L239", "weight": 1.0}, {"source": "brd_brd_6_user_roles", "target": "brd_brd_faculty", "relation": "contains", "confidence": "EXTRACTED", "source_file": "docs/architecture/brd/BRD.md", "source_location": "L249", "weight": 1.0}, {"source": "brd_brd_6_user_roles", "target": "brd_brd_accountant", "relation": "contains", "confidence": "EXTRACTED", "source_file": "docs/architecture/brd/BRD.md", "source_location": "L259", "weight": 1.0}, {"source": "brd_brd_6_user_roles", "target": "brd_brd_student", "relation": "contains", "confidence": "EXTRACTED", "source_file": "docs/architecture/brd/BRD.md", "source_location": "L270", "weight": 1.0}, {"source": "users_praveenkumar_documents_project_freelance_ims_v2_docs_architecture_brd_brd_md", "target": "brd_brd_7_functional_requirements", "relation": "contains", "confidence": "EXTRACTED", "source_file": "docs/architecture/brd/BRD.md", "source_location": "L282", "weight": 1.0}, {"source": "users_praveenkumar_documents_project_freelance_ims_v2_docs_architecture_brd_brd_md", "target": "brd_brd_fr_01_user_management", "relation": "contains", "confidence": "EXTRACTED", "source_file": "docs/architecture/brd/BRD.md", "source_location": "L286", "weight": 1.0}, {"source": "users_praveenkumar_documents_project_freelance_ims_v2_docs_architecture_brd_brd_md", "target": "brd_brd_fr_02_dynamic_role_management", "relation": "contains", "confidence": "EXTRACTED", "source_file": "docs/architecture/brd/BRD.md", "source_location": "L297", "weight": 1.0}, {"source": "users_praveenkumar_documents_project_freelance_ims_v2_docs_architecture_brd_brd_md", "target": "brd_brd_fr_03_branch_management", "relation": "contains", "confidence": "EXTRACTED", "source_file": "docs/architecture/brd/BRD.md", "source_location": "L310", "weight": 1.0}, {"source": "users_praveenkumar_documents_project_freelance_ims_v2_docs_architecture_brd_brd_md", "target": "brd_brd_fr_04_department_management", "relation": "contains", "confidence": "EXTRACTED", "source_file": "docs/architecture/brd/BRD.md", "source_location": "L320", "weight": 1.0}, {"source": "users_praveenkumar_documents_project_freelance_ims_v2_docs_architecture_brd_brd_md", "target": "brd_brd_fr_05_lead_management", "relation": "contains", "confidence": "EXTRACTED", "source_file": "docs/architecture/brd/BRD.md", "source_location": "L333", "weight": 1.0}, {"source": "brd_brd_fr_05_lead_management", "target": "brd_brd_lead_sources", "relation": "contains", "confidence": "EXTRACTED", "source_file": "docs/architecture/brd/BRD.md", "source_location": "L337", "weight": 1.0}, {"source": "brd_brd_fr_05_lead_management", "target": "brd_brd_lead_stages", "relation": "contains", "confidence": "EXTRACTED", "source_file": "docs/architecture/brd/BRD.md", "source_location": "L346", "weight": 1.0}, {"source": "brd_brd_fr_05_lead_management", "target": "brd_brd_follow_up_management", "relation": "contains", "confidence": "EXTRACTED", "source_file": "docs/architecture/brd/BRD.md", "source_location": "L359", "weight": 1.0}, {"source": "users_praveenkumar_documents_project_freelance_ims_v2_docs_architecture_brd_brd_md", "target": "brd_brd_fr_06_admission_management", "relation": "contains", "confidence": "EXTRACTED", "source_file": "docs/architecture/brd/BRD.md", "source_location": "L367", "weight": 1.0}, {"source": "users_praveenkumar_documents_project_freelance_ims_v2_docs_architecture_brd_brd_md", "target": "brd_brd_fr_07_student_management", "relation": "contains", "confidence": "EXTRACTED", "source_file": "docs/architecture/brd/BRD.md", "source_location": "L378", "weight": 1.0}, {"source": "brd_brd_fr_07_student_management", "target": "brd_brd_student_profile", "relation": "contains", "confidence": "EXTRACTED", "source_file": "docs/architecture/brd/BRD.md", "source_location": "L382", "weight": 1.0}, {"source": "brd_brd_fr_07_student_management", "target": "brd_brd_student_status", "relation": "contains", "confidence": "EXTRACTED", "source_file": "docs/architecture/brd/BRD.md", "source_location": "L388", "weight": 1.0}, {"source": "users_praveenkumar_documents_project_freelance_ims_v2_docs_architecture_brd_brd_md", "target": "brd_brd_fr_08_corporate_customer_management", "relation": "contains", "confidence": "EXTRACTED", "source_file": "docs/architecture/brd/BRD.md", "source_location": "L404", "weight": 1.0}, {"source": "brd_brd_fr_08_corporate_customer_management", "target": "brd_brd_corporate_profiles", "relation": "contains", "confidence": "EXTRACTED", "source_file": "docs/architecture/brd/BRD.md", "source_location": "L408", "weight": 1.0}, {"source": "brd_brd_fr_08_corporate_customer_management", "target": "brd_brd_corporate_contracts", "relation": "contains", "confidence": "EXTRACTED", "source_file": "docs/architecture/brd/BRD.md", "source_location": "L413", "weight": 1.0}, {"source": "brd_brd_fr_08_corporate_customer_management", "target": "brd_brd_corporate_employees", "relation": "contains", "confidence": "EXTRACTED", "source_file": "docs/architecture/brd/BRD.md", "source_location": "L420", "weight": 1.0}, {"source": "users_praveenkumar_documents_project_freelance_ims_v2_docs_architecture_brd_brd_md", "target": "brd_brd_fr_09_course_management", "relation": "contains", "confidence": "EXTRACTED", "source_file": "docs/architecture/brd/BRD.md", "source_location": "L427", "weight": 1.0}, {"source": "brd_brd_fr_09_course_management", "target": "brd_brd_course_types", "relation": "contains", "confidence": "EXTRACTED", "source_file": "docs/architecture/brd/BRD.md", "source_location": "L431", "weight": 1.0}, {"source": "brd_brd_fr_09_course_management", "target": "brd_brd_duration_types", "relation": "contains", "confidence": "EXTRACTED", "source_file": "docs/architecture/brd/BRD.md", "source_location": "L439", "weight": 1.0}, {"source": "users_praveenkumar_documents_project_freelance_ims_v2_docs_architecture_brd_brd_md", "target": "brd_brd_fr_10_batch_management", "relation": "contains", "confidence": "EXTRACTED", "source_file": "docs/architecture/brd/BRD.md", "source_location": "L447", "weight": 1.0}, {"source": "brd_brd_fr_10_batch_management", "target": "brd_brd_batch_features", "relation": "contains", "confidence": "EXTRACTED", "source_file": "docs/architecture/brd/BRD.md", "source_location": "L451", "weight": 1.0}, {"source": "users_praveenkumar_documents_project_freelance_ims_v2_docs_architecture_brd_brd_md", "target": "brd_brd_fr_11_timetable_management", "relation": "contains", "confidence": "EXTRACTED", "source_file": "docs/architecture/brd/BRD.md", "source_location": "L459", "weight": 1.0}, {"source": "brd_brd_fr_11_timetable_management", "target": "brd_brd_conflict_detection", "relation": "contains", "confidence": "EXTRACTED", "source_file": "docs/architecture/brd/BRD.md", "source_location": "L467", "weight": 1.0}, {"source": "users_praveenkumar_documents_project_freelance_ims_v2_docs_architecture_brd_brd_md", "target": "brd_brd_fr_12_attendance_management", "relation": "contains", "confidence": "EXTRACTED", "source_file": "docs/architecture/brd/BRD.md", "source_location": "L477", "weight": 1.0}, {"source": "users_praveenkumar_documents_project_freelance_ims_v2_docs_architecture_brd_brd_md", "target": "brd_brd_fr_13_fee_management", "relation": "contains", "confidence": "EXTRACTED", "source_file": "docs/architecture/brd/BRD.md", "source_location": "L488", "weight": 1.0}, {"source": "brd_brd_fr_13_fee_management", "target": "brd_brd_fee_models", "relation": "contains", "confidence": "EXTRACTED", "source_file": "docs/architecture/brd/BRD.md", "source_location": "L492", "weight": 1.0}, {"source": "brd_brd_fr_13_fee_management", "target": "brd_brd_discounts", "relation": "contains", "confidence": "EXTRACTED", "source_file": "docs/architecture/brd/BRD.md", "source_location": "L497", "weight": 1.0}, {"source": "brd_brd_fr_13_fee_management", "target": "brd_brd_refunds", "relation": "contains", "confidence": "EXTRACTED", "source_file": "docs/architecture/brd/BRD.md", "source_location": "L506", "weight": 1.0}, {"source": "users_praveenkumar_documents_project_freelance_ims_v2_docs_architecture_brd_brd_md", "target": "brd_brd_fr_14_communication_module", "relation": "contains", "confidence": "EXTRACTED", "source_file": "docs/architecture/brd/BRD.md", "source_location": "L513", "weight": 1.0}, {"source": "brd_brd_fr_14_communication_module", "target": "brd_brd_channels", "relation": "contains", "confidence": "EXTRACTED", "source_file": "docs/architecture/brd/BRD.md", "source_location": "L517", "weight": 1.0}, {"source": "brd_brd_fr_14_communication_module", "target": "brd_brd_features", "relation": "contains", "confidence": "EXTRACTED", "source_file": "docs/architecture/brd/BRD.md", "source_location": "L523", "weight": 1.0}, {"source": "users_praveenkumar_documents_project_freelance_ims_v2_docs_architecture_brd_brd_md", "target": "brd_brd_fr_15_certificate_management", "relation": "contains", "confidence": "EXTRACTED", "source_file": "docs/architecture/brd/BRD.md", "source_location": "L532", "weight": 1.0}, {"source": "brd_brd_fr_15_certificate_management", "target": "brd_brd_auto_certificate_generation", "relation": "contains", "confidence": "EXTRACTED", "source_file": "docs/architecture/brd/BRD.md", "source_location": "L536", "weight": 1.0}, {"source": "brd_brd_fr_15_certificate_management", "target": "brd_brd_eligibility_rules", "relation": "contains", "confidence": "EXTRACTED", "source_file": "docs/architecture/brd/BRD.md", "source_location": "L540", "weight": 1.0}, {"source": "brd_brd_fr_15_certificate_management", "target": "brd_brd_verification", "relation": "contains", "confidence": "EXTRACTED", "source_file": "docs/architecture/brd/BRD.md", "source_location": "L547", "weight": 1.0}, {"source": "users_praveenkumar_documents_project_freelance_ims_v2_docs_architecture_brd_brd_md", "target": "brd_brd_fr_16_document_management", "relation": "contains", "confidence": "EXTRACTED", "source_file": "docs/architecture/brd/BRD.md", "source_location": "L554", "weight": 1.0}, {"source": "brd_brd_fr_16_document_management", "target": "brd_brd_student_documents", "relation": "contains", "confidence": "EXTRACTED", "source_file": "docs/architecture/brd/BRD.md", "source_location": "L558", "weight": 1.0}, {"source": "brd_brd_fr_16_document_management", "target": "brd_brd_approval_workflow", "relation": "contains", "confidence": "EXTRACTED", "source_file": "docs/architecture/brd/BRD.md", "source_location": "L562", "weight": 1.0}, {"source": "users_praveenkumar_documents_project_freelance_ims_v2_docs_architecture_brd_brd_md", "target": "brd_brd_fr_17_reporting_dashboard", "relation": "contains", "confidence": "EXTRACTED", "source_file": "docs/architecture/brd/BRD.md", "source_location": "L573", "weight": 1.0}, {"source": "brd_brd_fr_17_reporting_dashboard", "target": "brd_brd_operational_reports", "relation": "contains", "confidence": "EXTRACTED", "source_file": "docs/architecture/brd/BRD.md", "source_location": "L577", "weight": 1.0}, {"source": "brd_brd_fr_17_reporting_dashboard", "target": "brd_brd_business_reports", "relation": "contains", "confidence": "EXTRACTED", "source_file": "docs/architecture/brd/BRD.md", "source_location": "L584", "weight": 1.0}, {"source": "users_praveenkumar_documents_project_freelance_ims_v2_docs_architecture_brd_brd_md", "target": "brd_brd_8_non_functional_requirements", "relation": "contains", "confidence": "EXTRACTED", "source_file": "docs/architecture/brd/BRD.md", "source_location": "L594", "weight": 1.0}, {"source": "brd_brd_8_non_functional_requirements", "target": "brd_brd_performance", "relation": "contains", "confidence": "EXTRACTED", "source_file": "docs/architecture/brd/BRD.md", "source_location": "L596", "weight": 1.0}, {"source": "brd_brd_8_non_functional_requirements", "target": "brd_brd_security", "relation": "contains", "confidence": "EXTRACTED", "source_file": "docs/architecture/brd/BRD.md", "source_location": "L606", "weight": 1.0}, {"source": "brd_brd_8_non_functional_requirements", "target": "brd_brd_auditability", "relation": "contains", "confidence": "EXTRACTED", "source_file": "docs/architecture/brd/BRD.md", "source_location": "L616", "weight": 1.0}, {"source": "brd_brd_8_non_functional_requirements", "target": "brd_brd_localization", "relation": "contains", "confidence": "EXTRACTED", "source_file": "docs/architecture/brd/BRD.md", "source_location": "L627", "weight": 1.0}, {"source": "brd_brd_8_non_functional_requirements", "target": "brd_brd_availability", "relation": "contains", "confidence": "EXTRACTED", "source_file": "docs/architecture/brd/BRD.md", "source_location": "L637", "weight": 1.0}, {"source": "users_praveenkumar_documents_project_freelance_ims_v2_docs_architecture_brd_brd_md", "target": "brd_brd_9_success_metrics", "relation": "contains", "confidence": "EXTRACTED", "source_file": "docs/architecture/brd/BRD.md", "source_location": "L647", "weight": 1.0}, {"source": "brd_brd_9_success_metrics", "target": "brd_brd_lead_management", "relation": "contains", "confidence": "EXTRACTED", "source_file": "docs/architecture/brd/BRD.md", "source_location": "L651", "weight": 1.0}, {"source": "brd_brd_9_success_metrics", "target": "brd_brd_admissions", "relation": "contains", "confidence": "EXTRACTED", "source_file": "docs/architecture/brd/BRD.md", "source_location": "L655", "weight": 1.0}, {"source": "brd_brd_9_success_metrics", "target": "brd_brd_attendance", "relation": "contains", "confidence": "EXTRACTED", "source_file": "docs/architecture/brd/BRD.md", "source_location": "L659", "weight": 1.0}, {"source": "brd_brd_9_success_metrics", "target": "brd_brd_finance_663", "relation": "contains", "confidence": "EXTRACTED", "source_file": "docs/architecture/brd/BRD.md", "source_location": "L663", "weight": 1.0}, {"source": "brd_brd_9_success_metrics", "target": "brd_brd_reporting_667", "relation": "contains", "confidence": "EXTRACTED", "source_file": "docs/architecture/brd/BRD.md", "source_location": "L667", "weight": 1.0}, {"source": "users_praveenkumar_documents_project_freelance_ims_v2_docs_architecture_brd_brd_md", "target": "brd_brd_10_future_roadmap", "relation": "contains", "confidence": "EXTRACTED", "source_file": "docs/architecture/brd/BRD.md", "source_location": "L673", "weight": 1.0}, {"source": "brd_brd_10_future_roadmap", "target": "brd_brd_phase_2", "relation": "contains", "confidence": "EXTRACTED", "source_file": "docs/architecture/brd/BRD.md", "source_location": "L675", "weight": 1.0}, {"source": "brd_brd_10_future_roadmap", "target": "brd_brd_phase_3", "relation": "contains", "confidence": "EXTRACTED", "source_file": "docs/architecture/brd/BRD.md", "source_location": "L682", "weight": 1.0}, {"source": "brd_brd_10_future_roadmap", "target": "brd_brd_phase_4", "relation": "contains", "confidence": "EXTRACTED", "source_file": "docs/architecture/brd/BRD.md", "source_location": "L690", "weight": 1.0}, {"source": "users_praveenkumar_documents_project_freelance_ims_v2_docs_architecture_brd_brd_md", "target": "brd_brd_11_review_alignment_addendum", "relation": "contains", "confidence": "EXTRACTED", "source_file": "docs/architecture/brd/BRD.md", "source_location": "L699", "weight": 1.0}, {"source": "brd_brd_11_review_alignment_addendum", "target": "brd_brd_b2b_corporate_training_requirements", "relation": "contains", "confidence": "EXTRACTED", "source_file": "docs/architecture/brd/BRD.md", "source_location": "L703", "weight": 1.0}, {"source": "brd_brd_11_review_alignment_addendum", "target": "brd_brd_compliance_and_document_expiry_requirements", "relation": "contains", "confidence": "EXTRACTED", "source_file": "docs/architecture/brd/BRD.md", "source_location": "L716", "weight": 1.0}, {"source": "brd_brd_11_review_alignment_addendum", "target": "brd_brd_bilingual_data_requirements", "relation": "contains", "confidence": "EXTRACTED", "source_file": "docs/architecture/brd/BRD.md", "source_location": "L722", "weight": 1.0}, {"source": "brd_brd_11_review_alignment_addendum", "target": "brd_brd_offline_attendance_and_tally_reliability", "relation": "contains", "confidence": "EXTRACTED", "source_file": "docs/architecture/brd/BRD.md", "source_location": "L726", "weight": 1.0}], "input_tokens": 0, "output_tokens": 0}