{"nodes": [{"id": "users_praveenkumar_documents_project_freelance_ims_v2_docs_architecture_frd_module_11_corporate_training_management_md", "label": "Module 11: Corporate Training Management.md", "file_type": "document", "source_file": "docs/architecture/frd/Module 11: Corporate Training Management.md", "source_location": "L1"}, {"id": "frd_module_11_corporate_training_management_functional_requirement_document", "label": "Functional Requirement Document", "file_type": "document", "source_file": "docs/architecture/frd/Module 11: Corporate Training Management.md", "source_location": "L1"}, {"id": "frd_module_11_corporate_training_management_module_11_corporate_training_management", "label": "Module 11: Corporate Training Management", "file_type": "document", "source_file": "docs/architecture/frd/Module 11: Corporate Training Management.md", "source_location": "L3"}, {"id": "frd_module_11_corporate_training_management_1_business_purpose", "label": "1. Business Purpose", "file_type": "document", "source_file": "docs/architecture/frd/Module 11: Corporate Training Management.md", "source_location": "L33"}, {"id": "frd_module_11_corporate_training_management_2_scope", "label": "2. Scope", "file_type": "document", "source_file": "docs/architecture/frd/Module 11: Corporate Training Management.md", "source_location": "L43"}, {"id": "frd_module_11_corporate_training_management_2_1_in_scope", "label": "2.1 In Scope", "file_type": "document", "source_file": "docs/architecture/frd/Module 11: Corporate Training Management.md", "source_location": "L45"}, {"id": "frd_module_11_corporate_training_management_2_2_out_of_scope_for_phase_1", "label": "2.2 Out of Scope for Phase 1", "file_type": "document", "source_file": "docs/architecture/frd/Module 11: Corporate Training Management.md", "source_location": "L59"}, {"id": "frd_module_11_corporate_training_management_3_business_principles", "label": "3. Business Principles", "file_type": "document", "source_file": "docs/architecture/frd/Module 11: Corporate Training Management.md", "source_location": "L69"}, {"id": "frd_module_11_corporate_training_management_4_owned_concepts", "label": "4. Owned Concepts", "file_type": "document", "source_file": "docs/architecture/frd/Module 11: Corporate Training Management.md", "source_location": "L84"}, {"id": "frd_module_11_corporate_training_management_5_business_model", "label": "5. Business Model", "file_type": "document", "source_file": "docs/architecture/frd/Module 11: Corporate Training Management.md", "source_location": "L106"}, {"id": "frd_module_11_corporate_training_management_5_1_corporate_account_lifecycle", "label": "5.1 Corporate Account Lifecycle", "file_type": "document", "source_file": "docs/architecture/frd/Module 11: Corporate Training Management.md", "source_location": "L108"}, {"id": "frd_module_11_corporate_training_management_5_2_corporate_contract_lifecycle", "label": "5.2 Corporate Contract Lifecycle", "file_type": "document", "source_file": "docs/architecture/frd/Module 11: Corporate Training Management.md", "source_location": "L125"}, {"id": "frd_module_11_corporate_training_management_5_3_program_lifecycle", "label": "5.3 Program Lifecycle", "file_type": "document", "source_file": "docs/architecture/frd/Module 11: Corporate Training Management.md", "source_location": "L152"}, {"id": "frd_module_11_corporate_training_management_5_4_corporate_participant_lifecycle", "label": "5.4 Corporate Participant Lifecycle", "file_type": "document", "source_file": "docs/architecture/frd/Module 11: Corporate Training Management.md", "source_location": "L170"}, {"id": "frd_module_11_corporate_training_management_6_screens", "label": "6. Screens", "file_type": "document", "source_file": "docs/architecture/frd/Module 11: Corporate Training Management.md", "source_location": "L189"}, {"id": "frd_module_11_corporate_training_management_cor_ui_001_corporate_customer_list", "label": "COR-UI-001 Corporate Customer List", "file_type": "document", "source_file": "docs/architecture/frd/Module 11: Corporate Training Management.md", "source_location": "L191"}, {"id": "frd_module_11_corporate_training_management_purpose", "label": "Purpose", "file_type": "document", "source_file": "docs/architecture/frd/Module 11: Corporate Training Management.md", "source_location": "L193"}, {"id": "frd_module_11_corporate_training_management_columns", "label": "Columns", "file_type": "document", "source_file": "docs/architecture/frd/Module 11: Corporate Training Management.md", "source_location": "L197"}, {"id": "frd_module_11_corporate_training_management_filters", "label": "Filters", "file_type": "document", "source_file": "docs/architecture/frd/Module 11: Corporate Training Management.md", "source_location": "L211"}, {"id": "frd_module_11_corporate_training_management_actions", "label": "Actions", "file_type": "document", "source_file": "docs/architecture/frd/Module 11: Corporate Training Management.md", "source_location": "L221"}, {"id": "frd_module_11_corporate_training_management_permissions", "label": "Permissions", "file_type": "document", "source_file": "docs/architecture/frd/Module 11: Corporate Training Management.md", "source_location": "L231"}, {"id": "frd_module_11_corporate_training_management_cor_ui_002_corporate_customer_screen", "label": "COR-UI-002 Corporate Customer Screen", "file_type": "document", "source_file": "docs/architecture/frd/Module 11: Corporate Training Management.md", "source_location": "L242"}, {"id": "frd_module_11_corporate_training_management_fields", "label": "Fields", "file_type": "document", "source_file": "docs/architecture/frd/Module 11: Corporate Training Management.md", "source_location": "L244"}, {"id": "frd_module_11_corporate_training_management_business_rules", "label": "Business Rules", "file_type": "document", "source_file": "docs/architecture/frd/Module 11: Corporate Training Management.md", "source_location": "L263"}, {"id": "frd_module_11_corporate_training_management_cor_ui_003_contact_person_screen", "label": "COR-UI-003 Contact Person Screen", "file_type": "document", "source_file": "docs/architecture/frd/Module 11: Corporate Training Management.md", "source_location": "L272"}, {"id": "frd_module_11_corporate_training_management_fields_274", "label": "Fields", "file_type": "document", "source_file": "docs/architecture/frd/Module 11: Corporate Training Management.md", "source_location": "L274"}, {"id": "frd_module_11_corporate_training_management_business_rules_287", "label": "Business Rules", "file_type": "document", "source_file": "docs/architecture/frd/Module 11: Corporate Training Management.md", "source_location": "L287"}, {"id": "frd_module_11_corporate_training_management_cor_ui_004_contract_list", "label": "COR-UI-004 Contract List", "file_type": "document", "source_file": "docs/architecture/frd/Module 11: Corporate Training Management.md", "source_location": "L294"}, {"id": "frd_module_11_corporate_training_management_columns_296", "label": "Columns", "file_type": "document", "source_file": "docs/architecture/frd/Module 11: Corporate Training Management.md", "source_location": "L296"}, {"id": "frd_module_11_corporate_training_management_actions_308", "label": "Actions", "file_type": "document", "source_file": "docs/architecture/frd/Module 11: Corporate Training Management.md", "source_location": "L308"}, {"id": "frd_module_11_corporate_training_management_cor_ui_005_contract_screen", "label": "COR-UI-005 Contract Screen", "file_type": "document", "source_file": "docs/architecture/frd/Module 11: Corporate Training Management.md", "source_location": "L320"}, {"id": "frd_module_11_corporate_training_management_contract_information", "label": "Contract Information", "file_type": "document", "source_file": "docs/architecture/frd/Module 11: Corporate Training Management.md", "source_location": "L322"}, {"id": "frd_module_11_corporate_training_management_billing_model", "label": "Billing Model", "file_type": "document", "source_file": "docs/architecture/frd/Module 11: Corporate Training Management.md", "source_location": "L335"}, {"id": "frd_module_11_corporate_training_management_sla_information", "label": "SLA Information", "file_type": "document", "source_file": "docs/architecture/frd/Module 11: Corporate Training Management.md", "source_location": "L344"}, {"id": "frd_module_11_corporate_training_management_business_rules_352", "label": "Business Rules", "file_type": "document", "source_file": "docs/architecture/frd/Module 11: Corporate Training Management.md", "source_location": "L352"}, {"id": "frd_module_11_corporate_training_management_cor_ui_006_program_management", "label": "COR-UI-006 Program Management", "file_type": "document", "source_file": "docs/architecture/frd/Module 11: Corporate Training Management.md", "source_location": "L361"}, {"id": "frd_module_11_corporate_training_management_purpose_363", "label": "Purpose", "file_type": "document", "source_file": "docs/architecture/frd/Module 11: Corporate Training Management.md", "source_location": "L363"}, {"id": "frd_module_11_corporate_training_management_fields_367", "label": "Fields", "file_type": "document", "source_file": "docs/architecture/frd/Module 11: Corporate Training Management.md", "source_location": "L367"}, {"id": "frd_module_11_corporate_training_management_business_rules_379", "label": "Business Rules", "file_type": "document", "source_file": "docs/architecture/frd/Module 11: Corporate Training Management.md", "source_location": "L379"}, {"id": "frd_module_11_corporate_training_management_cor_ui_007_corporate_batch_reference", "label": "COR-UI-007 Corporate Batch Reference", "file_type": "document", "source_file": "docs/architecture/frd/Module 11: Corporate Training Management.md", "source_location": "L387"}, {"id": "frd_module_11_corporate_training_management_additional_fields", "label": "Additional Fields", "file_type": "document", "source_file": "docs/architecture/frd/Module 11: Corporate Training Management.md", "source_location": "L389"}, {"id": "frd_module_11_corporate_training_management_business_rules_400", "label": "Business Rules", "file_type": "document", "source_file": "docs/architecture/frd/Module 11: Corporate Training Management.md", "source_location": "L400"}, {"id": "frd_module_11_corporate_training_management_cor_ui_008_participant_list", "label": "COR-UI-008 Participant List", "file_type": "document", "source_file": "docs/architecture/frd/Module 11: Corporate Training Management.md", "source_location": "L408"}, {"id": "frd_module_11_corporate_training_management_columns_410", "label": "Columns", "file_type": "document", "source_file": "docs/architecture/frd/Module 11: Corporate Training Management.md", "source_location": "L410"}, {"id": "frd_module_11_corporate_training_management_actions_423", "label": "Actions", "file_type": "document", "source_file": "docs/architecture/frd/Module 11: Corporate Training Management.md", "source_location": "L423"}, {"id": "frd_module_11_corporate_training_management_permissions_432", "label": "Permissions", "file_type": "document", "source_file": "docs/architecture/frd/Module 11: Corporate Training Management.md", "source_location": "L432"}, {"id": "frd_module_11_corporate_training_management_cor_ui_009_participant_screen", "label": "COR-UI-009 Participant Screen", "file_type": "document", "source_file": "docs/architecture/frd/Module 11: Corporate Training Management.md", "source_location": "L443"}, {"id": "frd_module_11_corporate_training_management_fields_445", "label": "Fields", "file_type": "document", "source_file": "docs/architecture/frd/Module 11: Corporate Training Management.md", "source_location": "L445"}, {"id": "frd_module_11_corporate_training_management_business_rules_458", "label": "Business Rules", "file_type": "document", "source_file": "docs/architecture/frd/Module 11: Corporate Training Management.md", "source_location": "L458"}, {"id": "frd_module_11_corporate_training_management_cor_ui_010_import_participants", "label": "COR-UI-010 Import Participants", "file_type": "document", "source_file": "docs/architecture/frd/Module 11: Corporate Training Management.md", "source_location": "L466"}, {"id": "frd_module_11_corporate_training_management_supported_formats", "label": "Supported Formats", "file_type": "document", "source_file": "docs/architecture/frd/Module 11: Corporate Training Management.md", "source_location": "L468"}, {"id": "frd_module_11_corporate_training_management_import_fields", "label": "Import Fields", "file_type": "document", "source_file": "docs/architecture/frd/Module 11: Corporate Training Management.md", "source_location": "L475"}, {"id": "frd_module_11_corporate_training_management_business_rules_486", "label": "Business Rules", "file_type": "document", "source_file": "docs/architecture/frd/Module 11: Corporate Training Management.md", "source_location": "L486"}, {"id": "frd_module_11_corporate_training_management_cor_ui_011_completion_dashboard", "label": "COR-UI-011 Completion Dashboard", "file_type": "document", "source_file": "docs/architecture/frd/Module 11: Corporate Training Management.md", "source_location": "L494"}, {"id": "frd_module_11_corporate_training_management_metrics", "label": "Metrics", "file_type": "document", "source_file": "docs/architecture/frd/Module 11: Corporate Training Management.md", "source_location": "L496"}, {"id": "frd_module_11_corporate_training_management_business_rules_506", "label": "Business Rules", "file_type": "document", "source_file": "docs/architecture/frd/Module 11: Corporate Training Management.md", "source_location": "L506"}, {"id": "frd_module_11_corporate_training_management_cor_ui_012_invoice_management", "label": "COR-UI-012 Invoice Management", "file_type": "document", "source_file": "docs/architecture/frd/Module 11: Corporate Training Management.md", "source_location": "L513"}, {"id": "frd_module_11_corporate_training_management_invoice_types", "label": "Invoice Types", "file_type": "document", "source_file": "docs/architecture/frd/Module 11: Corporate Training Management.md", "source_location": "L515"}, {"id": "frd_module_11_corporate_training_management_fields_523", "label": "Fields", "file_type": "document", "source_file": "docs/architecture/frd/Module 11: Corporate Training Management.md", "source_location": "L523"}, {"id": "frd_module_11_corporate_training_management_business_rules_536", "label": "Business Rules", "file_type": "document", "source_file": "docs/architecture/frd/Module 11: Corporate Training Management.md", "source_location": "L536"}, {"id": "frd_module_11_corporate_training_management_7_functional_requirements", "label": "7. Functional Requirements", "file_type": "document", "source_file": "docs/architecture/frd/Module 11: Corporate Training Management.md", "source_location": "L544"}, {"id": "frd_module_11_corporate_training_management_fr_cor_001_corporate_customer_creation", "label": "FR-COR-001 Corporate Customer Creation", "file_type": "document", "source_file": "docs/architecture/frd/Module 11: Corporate Training Management.md", "source_location": "L546"}, {"id": "frd_module_11_corporate_training_management_fr_cor_002_contact_management", "label": "FR-COR-002 Contact Management", "file_type": "document", "source_file": "docs/architecture/frd/Module 11: Corporate Training Management.md", "source_location": "L550"}, {"id": "frd_module_11_corporate_training_management_fr_cor_003_contract_management", "label": "FR-COR-003 Contract Management", "file_type": "document", "source_file": "docs/architecture/frd/Module 11: Corporate Training Management.md", "source_location": "L554"}, {"id": "frd_module_11_corporate_training_management_fr_cor_004_billing_models", "label": "FR-COR-004 Billing Models", "file_type": "document", "source_file": "docs/architecture/frd/Module 11: Corporate Training Management.md", "source_location": "L558"}, {"id": "frd_module_11_corporate_training_management_fr_cor_005_program_management", "label": "FR-COR-005 Program Management", "file_type": "document", "source_file": "docs/architecture/frd/Module 11: Corporate Training Management.md", "source_location": "L562"}, {"id": "frd_module_11_corporate_training_management_fr_cor_006_corporate_batch_reference", "label": "FR-COR-006 Corporate Batch Reference", "file_type": "document", "source_file": "docs/architecture/frd/Module 11: Corporate Training Management.md", "source_location": "L566"}, {"id": "frd_module_11_corporate_training_management_fr_cor_007_participant_management", "label": "FR-COR-007 Participant Management", "file_type": "document", "source_file": "docs/architecture/frd/Module 11: Corporate Training Management.md", "source_location": "L570"}, {"id": "frd_module_11_corporate_training_management_fr_cor_008_participant_import", "label": "FR-COR-008 Participant Import", "file_type": "document", "source_file": "docs/architecture/frd/Module 11: Corporate Training Management.md", "source_location": "L574"}, {"id": "frd_module_11_corporate_training_management_fr_cor_009_link_student_profile", "label": "FR-COR-009 Link Student Profile", "file_type": "document", "source_file": "docs/architecture/frd/Module 11: Corporate Training Management.md", "source_location": "L578"}, {"id": "frd_module_11_corporate_training_management_fr_cor_010_reporting_summary", "label": "FR-COR-010 Reporting Summary", "file_type": "document", "source_file": "docs/architecture/frd/Module 11: Corporate Training Management.md", "source_location": "L582"}, {"id": "frd_module_11_corporate_training_management_fr_cor_011_corporate_certificate_support", "label": "FR-COR-011 Corporate Certificate Support", "file_type": "document", "source_file": "docs/architecture/frd/Module 11: Corporate Training Management.md", "source_location": "L586"}, {"id": "frd_module_11_corporate_training_management_fr_cor_012_corporate_billing", "label": "FR-COR-012 Corporate Billing", "file_type": "document", "source_file": "docs/architecture/frd/Module 11: Corporate Training Management.md", "source_location": "L590"}, {"id": "frd_module_11_corporate_training_management_fr_cor_013_contract_renewal_tracking", "label": "FR-COR-013 Contract Renewal Tracking", "file_type": "document", "source_file": "docs/architecture/frd/Module 11: Corporate Training Management.md", "source_location": "L594"}, {"id": "frd_module_11_corporate_training_management_8_audit_events", "label": "8. Audit Events", "file_type": "document", "source_file": "docs/architecture/frd/Module 11: Corporate Training Management.md", "source_location": "L600"}, {"id": "frd_module_11_corporate_training_management_9_domain_errors", "label": "9. Domain Errors", "file_type": "document", "source_file": "docs/architecture/frd/Module 11: Corporate Training Management.md", "source_location": "L632"}, {"id": "frd_module_11_corporate_training_management_10_reporting_and_operational_views", "label": "10. Reporting and Operational Views", "file_type": "document", "source_file": "docs/architecture/frd/Module 11: Corporate Training Management.md", "source_location": "L657"}, {"id": "frd_module_11_corporate_training_management_11_frd_improvement_notes", "label": "11. FRD Improvement Notes", "file_type": "document", "source_file": "docs/architecture/frd/Module 11: Corporate Training Management.md", "source_location": "L677"}], "edges": [{"source": "users_praveenkumar_documents_project_freelance_ims_v2_docs_architecture_frd_module_11_corporate_training_management_md", "target": "frd_module_11_corporate_training_management_functional_requirement_document", "relation": "contains", "confidence": "EXTRACTED", "source_file": "docs/architecture/frd/Module 11: Corporate Training Management.md", "source_location": "L1", "weight": 1.0}, {"source": "frd_module_11_corporate_training_management_functional_requirement_document", "target": "frd_module_11_corporate_training_management_module_11_corporate_training_management", "relation": "contains", "confidence": "EXTRACTED", "source_file": "docs/architecture/frd/Module 11: Corporate Training Management.md", "source_location": "L3", "weight": 1.0}, {"source": "users_praveenkumar_documents_project_freelance_ims_v2_docs_architecture_frd_module_11_corporate_training_management_md", "target": "frd_module_11_corporate_training_management_1_business_purpose", "relation": "contains", "confidence": "EXTRACTED", "source_file": "docs/architecture/frd/Module 11: Corporate Training Management.md", "source_location": "L33", "weight": 1.0}, {"source": "users_praveenkumar_documents_project_freelance_ims_v2_docs_architecture_frd_module_11_corporate_training_management_md", "target": "frd_module_11_corporate_training_management_2_scope", "relation": "contains", "confidence": "EXTRACTED", "source_file": "docs/architecture/frd/Module 11: Corporate Training Management.md", "source_location": "L43", "weight": 1.0}, {"source": "frd_module_11_corporate_training_management_2_scope", "target": "frd_module_11_corporate_training_management_2_1_in_scope", "relation": "contains", "confidence": "EXTRACTED", "source_file": "docs/architecture/frd/Module 11: Corporate Training Management.md", "source_location": "L45", "weight": 1.0}, {"source": "frd_module_11_corporate_training_management_2_scope", "target": "frd_module_11_corporate_training_management_2_2_out_of_scope_for_phase_1", "relation": "contains", "confidence": "EXTRACTED", "source_file": "docs/architecture/frd/Module 11: Corporate Training Management.md", "source_location": "L59", "weight": 1.0}, {"source": "users_praveenkumar_documents_project_freelance_ims_v2_docs_architecture_frd_module_11_corporate_training_management_md", "target": "frd_module_11_corporate_training_management_3_business_principles", "relation": "contains", "confidence": "EXTRACTED", "source_file": "docs/architecture/frd/Module 11: Corporate Training Management.md", "source_location": "L69", "weight": 1.0}, {"source": "users_praveenkumar_documents_project_freelance_ims_v2_docs_architecture_frd_module_11_corporate_training_management_md", "target": "frd_module_11_corporate_training_management_4_owned_concepts", "relation": "contains", "confidence": "EXTRACTED", "source_file": "docs/architecture/frd/Module 11: Corporate Training Management.md", "source_location": "L84", "weight": 1.0}, {"source": "users_praveenkumar_documents_project_freelance_ims_v2_docs_architecture_frd_module_11_corporate_training_management_md", "target": "frd_module_11_corporate_training_management_5_business_model", "relation": "contains", "confidence": "EXTRACTED", "source_file": "docs/architecture/frd/Module 11: Corporate Training Management.md", "source_location": "L106", "weight": 1.0}, {"source": "frd_module_11_corporate_training_management_5_business_model", "target": "frd_module_11_corporate_training_management_5_1_corporate_account_lifecycle", "relation": "contains", "confidence": "EXTRACTED", "source_file": "docs/architecture/frd/Module 11: Corporate Training Management.md", "source_location": "L108", "weight": 1.0}, {"source": "frd_module_11_corporate_training_management_5_business_model", "target": "frd_module_11_corporate_training_management_5_2_corporate_contract_lifecycle", "relation": "contains", "confidence": "EXTRACTED", "source_file": "docs/architecture/frd/Module 11: Corporate Training Management.md", "source_location": "L125", "weight": 1.0}, {"source": "frd_module_11_corporate_training_management_5_business_model", "target": "frd_module_11_corporate_training_management_5_3_program_lifecycle", "relation": "contains", "confidence": "EXTRACTED", "source_file": "docs/architecture/frd/Module 11: Corporate Training Management.md", "source_location": "L152", "weight": 1.0}, {"source": "frd_module_11_corporate_training_management_5_business_model", "target": "frd_module_11_corporate_training_management_5_4_corporate_participant_lifecycle", "relation": "contains", "confidence": "EXTRACTED", "source_file": "docs/architecture/frd/Module 11: Corporate Training Management.md", "source_location": "L170", "weight": 1.0}, {"source": "users_praveenkumar_documents_project_freelance_ims_v2_docs_architecture_frd_module_11_corporate_training_management_md", "target": "frd_module_11_corporate_training_management_6_screens", "relation": "contains", "confidence": "EXTRACTED", "source_file": "docs/architecture/frd/Module 11: Corporate Training Management.md", "source_location": "L189", "weight": 1.0}, {"source": "frd_module_11_corporate_training_management_6_screens", "target": "frd_module_11_corporate_training_management_cor_ui_001_corporate_customer_list", "relation": "contains", "confidence": "EXTRACTED", "source_file": "docs/architecture/frd/Module 11: Corporate Training Management.md", "source_location": "L191", "weight": 1.0}, {"source": "frd_module_11_corporate_training_management_cor_ui_001_corporate_customer_list", "target": "frd_module_11_corporate_training_management_purpose", "relation": "contains", "confidence": "EXTRACTED", "source_file": "docs/architecture/frd/Module 11: Corporate Training Management.md", "source_location": "L193", "weight": 1.0}, {"source": "frd_module_11_corporate_training_management_cor_ui_001_corporate_customer_list", "target": "frd_module_11_corporate_training_management_columns", "relation": "contains", "confidence": "EXTRACTED", "source_file": "docs/architecture/frd/Module 11: Corporate Training Management.md", "source_location": "L197", "weight": 1.0}, {"source": "frd_module_11_corporate_training_management_cor_ui_001_corporate_customer_list", "target": "frd_module_11_corporate_training_management_filters", "relation": "contains", "confidence": "EXTRACTED", "source_file": "docs/architecture/frd/Module 11: Corporate Training Management.md", "source_location": "L211", "weight": 1.0}, {"source": "frd_module_11_corporate_training_management_cor_ui_001_corporate_customer_list", "target": "frd_module_11_corporate_training_management_actions", "relation": "contains", "confidence": "EXTRACTED", "source_file": "docs/architecture/frd/Module 11: Corporate Training Management.md", "source_location": "L221", "weight": 1.0}, {"source": "frd_module_11_corporate_training_management_cor_ui_001_corporate_customer_list", "target": "frd_module_11_corporate_training_management_permissions", "relation": "contains", "confidence": "EXTRACTED", "source_file": "docs/architecture/frd/Module 11: Corporate Training Management.md", "source_location": "L231", "weight": 1.0}, {"source": "frd_module_11_corporate_training_management_6_screens", "target": "frd_module_11_corporate_training_management_cor_ui_002_corporate_customer_screen", "relation": "contains", "confidence": "EXTRACTED", "source_file": "docs/architecture/frd/Module 11: Corporate Training Management.md", "source_location": "L242", "weight": 1.0}, {"source": "frd_module_11_corporate_training_management_cor_ui_002_corporate_customer_screen", "target": "frd_module_11_corporate_training_management_fields", "relation": "contains", "confidence": "EXTRACTED", "source_file": "docs/architecture/frd/Module 11: Corporate Training Management.md", "source_location": "L244", "weight": 1.0}, {"source": "frd_module_11_corporate_training_management_cor_ui_002_corporate_customer_screen", "target": "frd_module_11_corporate_training_management_business_rules", "relation": "contains", "confidence": "EXTRACTED", "source_file": "docs/architecture/frd/Module 11: Corporate Training Management.md", "source_location": "L263", "weight": 1.0}, {"source": "frd_module_11_corporate_training_management_6_screens", "target": "frd_module_11_corporate_training_management_cor_ui_003_contact_person_screen", "relation": "contains", "confidence": "EXTRACTED", "source_file": "docs/architecture/frd/Module 11: Corporate Training Management.md", "source_location": "L272", "weight": 1.0}, {"source": "frd_module_11_corporate_training_management_cor_ui_003_contact_person_screen", "target": "frd_module_11_corporate_training_management_fields_274", "relation": "contains", "confidence": "EXTRACTED", "source_file": "docs/architecture/frd/Module 11: Corporate Training Management.md", "source_location": "L274", "weight": 1.0}, {"source": "frd_module_11_corporate_training_management_cor_ui_003_contact_person_screen", "target": "frd_module_11_corporate_training_management_business_rules_287", "relation": "contains", "confidence": "EXTRACTED", "source_file": "docs/architecture/frd/Module 11: Corporate Training Management.md", "source_location": "L287", "weight": 1.0}, {"source": "frd_module_11_corporate_training_management_6_screens", "target": "frd_module_11_corporate_training_management_cor_ui_004_contract_list", "relation": "contains", "confidence": "EXTRACTED", "source_file": "docs/architecture/frd/Module 11: Corporate Training Management.md", "source_location": "L294", "weight": 1.0}, {"source": "frd_module_11_corporate_training_management_cor_ui_004_contract_list", "target": "frd_module_11_corporate_training_management_columns_296", "relation": "contains", "confidence": "EXTRACTED", "source_file": "docs/architecture/frd/Module 11: Corporate Training Management.md", "source_location": "L296", "weight": 1.0}, {"source": "frd_module_11_corporate_training_management_cor_ui_004_contract_list", "target": "frd_module_11_corporate_training_management_actions_308", "relation": "contains", "confidence": "EXTRACTED", "source_file": "docs/architecture/frd/Module 11: Corporate Training Management.md", "source_location": "L308", "weight": 1.0}, {"source": "frd_module_11_corporate_training_management_6_screens", "target": "frd_module_11_corporate_training_management_cor_ui_005_contract_screen", "relation": "contains", "confidence": "EXTRACTED", "source_file": "docs/architecture/frd/Module 11: Corporate Training Management.md", "source_location": "L320", "weight": 1.0}, {"source": "frd_module_11_corporate_training_management_cor_ui_005_contract_screen", "target": "frd_module_11_corporate_training_management_contract_information", "relation": "contains", "confidence": "EXTRACTED", "source_file": "docs/architecture/frd/Module 11: Corporate Training Management.md", "source_location": "L322", "weight": 1.0}, {"source": "frd_module_11_corporate_training_management_cor_ui_005_contract_screen", "target": "frd_module_11_corporate_training_management_billing_model", "relation": "contains", "confidence": "EXTRACTED", "source_file": "docs/architecture/frd/Module 11: Corporate Training Management.md", "source_location": "L335", "weight": 1.0}, {"source": "frd_module_11_corporate_training_management_cor_ui_005_contract_screen", "target": "frd_module_11_corporate_training_management_sla_information", "relation": "contains", "confidence": "EXTRACTED", "source_file": "docs/architecture/frd/Module 11: Corporate Training Management.md", "source_location": "L344", "weight": 1.0}, {"source": "frd_module_11_corporate_training_management_cor_ui_005_contract_screen", "target": "frd_module_11_corporate_training_management_business_rules_352", "relation": "contains", "confidence": "EXTRACTED", "source_file": "docs/architecture/frd/Module 11: Corporate Training Management.md", "source_location": "L352", "weight": 1.0}, {"source": "frd_module_11_corporate_training_management_6_screens", "target": "frd_module_11_corporate_training_management_cor_ui_006_program_management", "relation": "contains", "confidence": "EXTRACTED", "source_file": "docs/architecture/frd/Module 11: Corporate Training Management.md", "source_location": "L361", "weight": 1.0}, {"source": "frd_module_11_corporate_training_management_cor_ui_006_program_management", "target": "frd_module_11_corporate_training_management_purpose_363", "relation": "contains", "confidence": "EXTRACTED", "source_file": "docs/architecture/frd/Module 11: Corporate Training Management.md", "source_location": "L363", "weight": 1.0}, {"source": "frd_module_11_corporate_training_management_cor_ui_006_program_management", "target": "frd_module_11_corporate_training_management_fields_367", "relation": "contains", "confidence": "EXTRACTED", "source_file": "docs/architecture/frd/Module 11: Corporate Training Management.md", "source_location": "L367", "weight": 1.0}, {"source": "frd_module_11_corporate_training_management_cor_ui_006_program_management", "target": "frd_module_11_corporate_training_management_business_rules_379", "relation": "contains", "confidence": "EXTRACTED", "source_file": "docs/architecture/frd/Module 11: Corporate Training Management.md", "source_location": "L379", "weight": 1.0}, {"source": "frd_module_11_corporate_training_management_6_screens", "target": "frd_module_11_corporate_training_management_cor_ui_007_corporate_batch_reference", "relation": "contains", "confidence": "EXTRACTED", "source_file": "docs/architecture/frd/Module 11: Corporate Training Management.md", "source_location": "L387", "weight": 1.0}, {"source": "frd_module_11_corporate_training_management_cor_ui_007_corporate_batch_reference", "target": "frd_module_11_corporate_training_management_additional_fields", "relation": "contains", "confidence": "EXTRACTED", "source_file": "docs/architecture/frd/Module 11: Corporate Training Management.md", "source_location": "L389", "weight": 1.0}, {"source": "frd_module_11_corporate_training_management_cor_ui_007_corporate_batch_reference", "target": "frd_module_11_corporate_training_management_business_rules_400", "relation": "contains", "confidence": "EXTRACTED", "source_file": "docs/architecture/frd/Module 11: Corporate Training Management.md", "source_location": "L400", "weight": 1.0}, {"source": "frd_module_11_corporate_training_management_6_screens", "target": "frd_module_11_corporate_training_management_cor_ui_008_participant_list", "relation": "contains", "confidence": "EXTRACTED", "source_file": "docs/architecture/frd/Module 11: Corporate Training Management.md", "source_location": "L408", "weight": 1.0}, {"source": "frd_module_11_corporate_training_management_cor_ui_008_participant_list", "target": "frd_module_11_corporate_training_management_columns_410", "relation": "contains", "confidence": "EXTRACTED", "source_file": "docs/architecture/frd/Module 11: Corporate Training Management.md", "source_location": "L410", "weight": 1.0}, {"source": "frd_module_11_corporate_training_management_cor_ui_008_participant_list", "target": "frd_module_11_corporate_training_management_actions_423", "relation": "contains", "confidence": "EXTRACTED", "source_file": "docs/architecture/frd/Module 11: Corporate Training Management.md", "source_location": "L423", "weight": 1.0}, {"source": "frd_module_11_corporate_training_management_cor_ui_008_participant_list", "target": "frd_module_11_corporate_training_management_permissions_432", "relation": "contains", "confidence": "EXTRACTED", "source_file": "docs/architecture/frd/Module 11: Corporate Training Management.md", "source_location": "L432", "weight": 1.0}, {"source": "frd_module_11_corporate_training_management_6_screens", "target": "frd_module_11_corporate_training_management_cor_ui_009_participant_screen", "relation": "contains", "confidence": "EXTRACTED", "source_file": "docs/architecture/frd/Module 11: Corporate Training Management.md", "source_location": "L443", "weight": 1.0}, {"source": "frd_module_11_corporate_training_management_cor_ui_009_participant_screen", "target": "frd_module_11_corporate_training_management_fields_445", "relation": "contains", "confidence": "EXTRACTED", "source_file": "docs/architecture/frd/Module 11: Corporate Training Management.md", "source_location": "L445", "weight": 1.0}, {"source": "frd_module_11_corporate_training_management_cor_ui_009_participant_screen", "target": "frd_module_11_corporate_training_management_business_rules_458", "relation": "contains", "confidence": "EXTRACTED", "source_file": "docs/architecture/frd/Module 11: Corporate Training Management.md", "source_location": "L458", "weight": 1.0}, {"source": "frd_module_11_corporate_training_management_6_screens", "target": "frd_module_11_corporate_training_management_cor_ui_010_import_participants", "relation": "contains", "confidence": "EXTRACTED", "source_file": "docs/architecture/frd/Module 11: Corporate Training Management.md", "source_location": "L466", "weight": 1.0}, {"source": "frd_module_11_corporate_training_management_cor_ui_010_import_participants", "target": "frd_module_11_corporate_training_management_supported_formats", "relation": "contains", "confidence": "EXTRACTED", "source_file": "docs/architecture/frd/Module 11: Corporate Training Management.md", "source_location": "L468", "weight": 1.0}, {"source": "frd_module_11_corporate_training_management_cor_ui_010_import_participants", "target": "frd_module_11_corporate_training_management_import_fields", "relation": "contains", "confidence": "EXTRACTED", "source_file": "docs/architecture/frd/Module 11: Corporate Training Management.md", "source_location": "L475", "weight": 1.0}, {"source": "frd_module_11_corporate_training_management_cor_ui_010_import_participants", "target": "frd_module_11_corporate_training_management_business_rules_486", "relation": "contains", "confidence": "EXTRACTED", "source_file": "docs/architecture/frd/Module 11: Corporate Training Management.md", "source_location": "L486", "weight": 1.0}, {"source": "frd_module_11_corporate_training_management_6_screens", "target": "frd_module_11_corporate_training_management_cor_ui_011_completion_dashboard", "relation": "contains", "confidence": "EXTRACTED", "source_file": "docs/architecture/frd/Module 11: Corporate Training Management.md", "source_location": "L494", "weight": 1.0}, {"source": "frd_module_11_corporate_training_management_cor_ui_011_completion_dashboard", "target": "frd_module_11_corporate_training_management_metrics", "relation": "contains", "confidence": "EXTRACTED", "source_file": "docs/architecture/frd/Module 11: Corporate Training Management.md", "source_location": "L496", "weight": 1.0}, {"source": "frd_module_11_corporate_training_management_cor_ui_011_completion_dashboard", "target": "frd_module_11_corporate_training_management_business_rules_506", "relation": "contains", "confidence": "EXTRACTED", "source_file": "docs/architecture/frd/Module 11: Corporate Training Management.md", "source_location": "L506", "weight": 1.0}, {"source": "frd_module_11_corporate_training_management_6_screens", "target": "frd_module_11_corporate_training_management_cor_ui_012_invoice_management", "relation": "contains", "confidence": "EXTRACTED", "source_file": "docs/architecture/frd/Module 11: Corporate Training Management.md", "source_location": "L513", "weight": 1.0}, {"source": "frd_module_11_corporate_training_management_cor_ui_012_invoice_management", "target": "frd_module_11_corporate_training_management_invoice_types", "relation": "contains", "confidence": "EXTRACTED", "source_file": "docs/architecture/frd/Module 11: Corporate Training Management.md", "source_location": "L515", "weight": 1.0}, {"source": "frd_module_11_corporate_training_management_cor_ui_012_invoice_management", "target": "frd_module_11_corporate_training_management_fields_523", "relation": "contains", "confidence": "EXTRACTED", "source_file": "docs/architecture/frd/Module 11: Corporate Training Management.md", "source_location": "L523", "weight": 1.0}, {"source": "frd_module_11_corporate_training_management_cor_ui_012_invoice_management", "target": "frd_module_11_corporate_training_management_business_rules_536", "relation": "contains", "confidence": "EXTRACTED", "source_file": "docs/architecture/frd/Module 11: Corporate Training Management.md", "source_location": "L536", "weight": 1.0}, {"source": "users_praveenkumar_documents_project_freelance_ims_v2_docs_architecture_frd_module_11_corporate_training_management_md", "target": "frd_module_11_corporate_training_management_7_functional_requirements", "relation": "contains", "confidence": "EXTRACTED", "source_file": "docs/architecture/frd/Module 11: Corporate Training Management.md", "source_location": "L544", "weight": 1.0}, {"source": "frd_module_11_corporate_training_management_7_functional_requirements", "target": "frd_module_11_corporate_training_management_fr_cor_001_corporate_customer_creation", "relation": "contains", "confidence": "EXTRACTED", "source_file": "docs/architecture/frd/Module 11: Corporate Training Management.md", "source_location": "L546", "weight": 1.0}, {"source": "frd_module_11_corporate_training_management_7_functional_requirements", "target": "frd_module_11_corporate_training_management_fr_cor_002_contact_management", "relation": "contains", "confidence": "EXTRACTED", "source_file": "docs/architecture/frd/Module 11: Corporate Training Management.md", "source_location": "L550", "weight": 1.0}, {"source": "frd_module_11_corporate_training_management_7_functional_requirements", "target": "frd_module_11_corporate_training_management_fr_cor_003_contract_management", "relation": "contains", "confidence": "EXTRACTED", "source_file": "docs/architecture/frd/Module 11: Corporate Training Management.md", "source_location": "L554", "weight": 1.0}, {"source": "frd_module_11_corporate_training_management_7_functional_requirements", "target": "frd_module_11_corporate_training_management_fr_cor_004_billing_models", "relation": "contains", "confidence": "EXTRACTED", "source_file": "docs/architecture/frd/Module 11: Corporate Training Management.md", "source_location": "L558", "weight": 1.0}, {"source": "frd_module_11_corporate_training_management_7_functional_requirements", "target": "frd_module_11_corporate_training_management_fr_cor_005_program_management", "relation": "contains", "confidence": "EXTRACTED", "source_file": "docs/architecture/frd/Module 11: Corporate Training Management.md", "source_location": "L562", "weight": 1.0}, {"source": "frd_module_11_corporate_training_management_7_functional_requirements", "target": "frd_module_11_corporate_training_management_fr_cor_006_corporate_batch_reference", "relation": "contains", "confidence": "EXTRACTED", "source_file": "docs/architecture/frd/Module 11: Corporate Training Management.md", "source_location": "L566", "weight": 1.0}, {"source": "frd_module_11_corporate_training_management_7_functional_requirements", "target": "frd_module_11_corporate_training_management_fr_cor_007_participant_management", "relation": "contains", "confidence": "EXTRACTED", "source_file": "docs/architecture/frd/Module 11: Corporate Training Management.md", "source_location": "L570", "weight": 1.0}, {"source": "frd_module_11_corporate_training_management_7_functional_requirements", "target": "frd_module_11_corporate_training_management_fr_cor_008_participant_import", "relation": "contains", "confidence": "EXTRACTED", "source_file": "docs/architecture/frd/Module 11: Corporate Training Management.md", "source_location": "L574", "weight": 1.0}, {"source": "frd_module_11_corporate_training_management_7_functional_requirements", "target": "frd_module_11_corporate_training_management_fr_cor_009_link_student_profile", "relation": "contains", "confidence": "EXTRACTED", "source_file": "docs/architecture/frd/Module 11: Corporate Training Management.md", "source_location": "L578", "weight": 1.0}, {"source": "frd_module_11_corporate_training_management_7_functional_requirements", "target": "frd_module_11_corporate_training_management_fr_cor_010_reporting_summary", "relation": "contains", "confidence": "EXTRACTED", "source_file": "docs/architecture/frd/Module 11: Corporate Training Management.md", "source_location": "L582", "weight": 1.0}, {"source": "frd_module_11_corporate_training_management_7_functional_requirements", "target": "frd_module_11_corporate_training_management_fr_cor_011_corporate_certificate_support", "relation": "contains", "confidence": "EXTRACTED", "source_file": "docs/architecture/frd/Module 11: Corporate Training Management.md", "source_location": "L586", "weight": 1.0}, {"source": "frd_module_11_corporate_training_management_7_functional_requirements", "target": "frd_module_11_corporate_training_management_fr_cor_012_corporate_billing", "relation": "contains", "confidence": "EXTRACTED", "source_file": "docs/architecture/frd/Module 11: Corporate Training Management.md", "source_location": "L590", "weight": 1.0}, {"source": "frd_module_11_corporate_training_management_7_functional_requirements", "target": "frd_module_11_corporate_training_management_fr_cor_013_contract_renewal_tracking", "relation": "contains", "confidence": "EXTRACTED", "source_file": "docs/architecture/frd/Module 11: Corporate Training Management.md", "source_location": "L594", "weight": 1.0}, {"source": "users_praveenkumar_documents_project_freelance_ims_v2_docs_architecture_frd_module_11_corporate_training_management_md", "target": "frd_module_11_corporate_training_management_8_audit_events", "relation": "contains", "confidence": "EXTRACTED", "source_file": "docs/architecture/frd/Module 11: Corporate Training Management.md", "source_location": "L600", "weight": 1.0}, {"source": "users_praveenkumar_documents_project_freelance_ims_v2_docs_architecture_frd_module_11_corporate_training_management_md", "target": "frd_module_11_corporate_training_management_9_domain_errors", "relation": "contains", "confidence": "EXTRACTED", "source_file": "docs/architecture/frd/Module 11: Corporate Training Management.md", "source_location": "L632", "weight": 1.0}, {"source": "users_praveenkumar_documents_project_freelance_ims_v2_docs_architecture_frd_module_11_corporate_training_management_md", "target": "frd_module_11_corporate_training_management_10_reporting_and_operational_views", "relation": "contains", "confidence": "EXTRACTED", "source_file": "docs/architecture/frd/Module 11: Corporate Training Management.md", "source_location": "L657", "weight": 1.0}, {"source": "users_praveenkumar_documents_project_freelance_ims_v2_docs_architecture_frd_module_11_corporate_training_management_md", "target": "frd_module_11_corporate_training_management_11_frd_improvement_notes", "relation": "contains", "confidence": "EXTRACTED", "source_file": "docs/architecture/frd/Module 11: Corporate Training Management.md", "source_location": "L677", "weight": 1.0}], "input_tokens": 0, "output_tokens": 0}